electricalc.py
mindpowered_electricalc/ElectriCalc.py
mindpowered_electricalc/__init__.py
mindpowered_electricalc-0.0.2.dist-info/LICENSE.txt
mindpowered_electricalc-0.0.2.dist-info/METADATA
mindpowered_electricalc-0.0.2.dist-info/WHEEL
mindpowered_electricalc-0.0.2.dist-info/top_level.txt
mindpowered_electricalc-0.0.2.dist-info/RECORD
